pkictl/__init__.py
pkictl/__main__.py
pkictl/cli.py
pkictl/models.py
pkictl/pkictl.py
pkictl/schemas.py
pkictl/utils.py
pkictl/vault.py
pkictl-0.2.1.dist-info/LICENSE
pkictl-0.2.1.dist-info/METADATA
pkictl-0.2.1.dist-info/WHEEL
pkictl-0.2.1.dist-info/entry_points.txt
pkictl-0.2.1.dist-info/top_level.txt
pkictl-0.2.1.dist-info/RECORD
