Metadata-Version: 2.1
Name: pkictl
Version: 0.2.1
Summary: A command-line utility for declaratively provisioning PKI in Hashicorp Vault
Home-page: http://github.com/bincyber/pkictl
Author: @bincyber
License: MPL
Keywords: vault pki kubernetes public key infrastructure security
Platform: any
Classifier: Development Status :: 4 - Beta
Classifier: Environment :: Console
Classifier: Intended Audience :: Developers
Classifier: Intended Audience :: System Administrators
Classifier: Natural Language :: English
Classifier: License :: OSI Approved :: Mozilla Public License 2.0 (MPL 2.0)
Classifier: Operating System :: MacOS
Classifier: Operating System :: POSIX
Classifier: Operating System :: Unix
Classifier: Programming Language :: Python
Classifier: Programming Language :: Python :: 3.6
Classifier: Programming Language :: Python :: 3.7
Classifier: Programming Language :: Python :: Implementation :: CPython
Classifier: Topic :: Security
Classifier: Topic :: Security :: Cryptography
Classifier: Topic :: System :: Systems Administration
Classifier: Topic :: Utilities
Requires-Python: >=3.6
Requires-Dist: PyYAML
Requires-Dist: requests
Requires-Dist: voluptuous
